flagger/__init__.py
flagger/flagger.py
flagger/encoding/__init__.py
flagger/encoding/encoding_checker.py
flagger/encoding/oct.py
flagger/modules/__init__.py
flagger/modules/banner.py
flagger/modules/binwalker.py
flagger/modules/ginwalker.py
flagger/modules/utils.py
juba0x00_flagger-2.1.dist-info/LICENSE
juba0x00_flagger-2.1.dist-info/METADATA
juba0x00_flagger-2.1.dist-info/WHEEL
juba0x00_flagger-2.1.dist-info/entry_points.txt
juba0x00_flagger-2.1.dist-info/top_level.txt
juba0x00_flagger-2.1.dist-info/RECORD
